telerembash/__init__.py
telerembash/_logging.py
telerembash/bot.py
telerembash/cli.py
telerembash/daemon.py
telerembash/version.py
telerembash/artifacts/__init__.py
telerembash/artifacts/initd.template
telerembash/artifacts/logging.config.yaml
telerembash/artifacts/service-initd.bash.template
telerembash/artifacts/service-prepare.bash.template
telerembash/artifacts/service-systemd.bash.template
telerembash/artifacts/systemd.service.template
telerembash/artifacts/welcome.sh.template
telerembash-0.2.4.dist-info/LICENSE
telerembash-0.2.4.dist-info/METADATA
telerembash-0.2.4.dist-info/WHEEL
telerembash-0.2.4.dist-info/entry_points.txt
telerembash-0.2.4.dist-info/top_level.txt
telerembash-0.2.4.dist-info/zip-safe
telerembash-0.2.4.dist-info/RECORD
