Metadata-Version: 2.1
Name: telerembash
Version: 0.2.4
Summary: A Telegram Remote Shell Bot with HOTP authentication.
Home-page: https://github.com/kpe/telerembash/
Author: kpe
Author-email: kpe.git@gmailbox.org
License: MIT
Keywords: telegram totp hotp authentication bot
Platform: UNKNOWN
Classifier: Development Status :: 5 - Production/Stable
Classifier: License :: OSI Approved :: MIT License
Classifier: Programming Language :: Python
Classifier: Programming Language :: Python :: 3
Classifier: Programming Language :: Python :: 3.7
Classifier: Programming Language :: Python :: 3.8
Classifier: Programming Language :: Python :: 3.9
Classifier: Programming Language :: Python :: Implementation :: CPython
Classifier: Programming Language :: Python :: Implementation :: PyPy
Requires-Python: >=3.5
Requires-Dist: aiogram (==2.11.2)
Requires-Dist: pyotp (==2.4.1)
Requires-Dist: PyYAML (==5.3.1)
Requires-Dist: py-params (==0.10.1)
Requires-Dist: coloredlogs (==15.0)
Requires-Dist: qrcode (==6.1)
Requires-Dist: python-daemon (==2.2.4)
